prefect_memory_profiling/__init__.py
prefect_memory_profiling/_version.py
prefect_memory_profiling/flows.py
prefect_memory_profiling/tasks.py
prefect_memory_profiling-1.0.0.dist-info/LICENSE
prefect_memory_profiling-1.0.0.dist-info/METADATA
prefect_memory_profiling-1.0.0.dist-info/WHEEL
prefect_memory_profiling-1.0.0.dist-info/top_level.txt
prefect_memory_profiling-1.0.0.dist-info/RECORD
